pytonapi/__init__.py
pytonapi/base.py
pytonapi/exceptions.py
pytonapi/logger.py
pytonapi/py.typed
pytonapi/tonapi.py
pytonapi/utils.py
pytonapi/methods/__init__.py
pytonapi/methods/accounts.py
pytonapi/methods/blockchain.py
pytonapi/methods/dns.py
pytonapi/methods/emulate.py
pytonapi/methods/events.py
pytonapi/methods/extra_currency.py
pytonapi/methods/gasless.py
pytonapi/methods/jettons.py
pytonapi/methods/liteserver.py
pytonapi/methods/multisig.py
pytonapi/methods/nft.py
pytonapi/methods/purchases.py
pytonapi/methods/rates.py
pytonapi/methods/sse.py
pytonapi/methods/staking.py
pytonapi/methods/storage.py
pytonapi/methods/tonconnect.py
pytonapi/methods/traces.py
pytonapi/methods/utilites.py
pytonapi/methods/wallet.py
pytonapi/methods/webhooks.py
pytonapi/methods/websocket.py
pytonapi/schema/__init__.py
pytonapi/schema/_address.py
pytonapi/schema/_balance.py
pytonapi/schema/accounts.py
pytonapi/schema/blockchain.py
pytonapi/schema/dns.py
pytonapi/schema/domains.py
pytonapi/schema/events.py
pytonapi/schema/extra_currency.py
pytonapi/schema/gasless.py
pytonapi/schema/jettons.py
pytonapi/schema/liteserver.py
pytonapi/schema/multisig.py
pytonapi/schema/nft.py
pytonapi/schema/purchases.py
pytonapi/schema/rates.py
pytonapi/schema/staking.py
pytonapi/schema/storage.py
pytonapi/schema/tonconnect.py
pytonapi/schema/traces.py
pytonapi/schema/utilites.py
pytonapi/schema/wallet.py
pytonapi/schema/webhooks.py
pytonapi-0.5.0.dist-info/LICENSE
pytonapi-0.5.0.dist-info/METADATA
pytonapi-0.5.0.dist-info/WHEEL
pytonapi-0.5.0.dist-info/top_level.txt
pytonapi-0.5.0.dist-info/RECORD
