Metadata-Version: 2.1
Name: pytonapi
Version: 0.5.0
Summary: Provide access to indexed TON blockchain.
Home-page: https://github.com/tonkeeper/pytonapi/
Author: nessshon
Classifier: Programming Language :: Python :: 3.9
Classifier: Programming Language :: Python :: 3.10
Classifier: Programming Language :: Python :: 3.11
Classifier: Programming Language :: Python :: 3.12
Classifier: Programming Language :: Python :: 3.13
Classifier: License :: OSI Approved :: MIT License
Classifier: Operating System :: OS Independent
License-File: LICENSE
Requires-Dist: aiohttp <=3.12.2,>=3.9.0
Requires-Dist: pydantic <=2.11.5,>=2.4.1
